pypkgs_sa/__init__.py
pypkgs_sa/pypkgs_sa.py
pypkgs_sa-0.1.0.dist-info/LICENSE
pypkgs_sa-0.1.0.dist-info/WHEEL
pypkgs_sa-0.1.0.dist-info/METADATA
pypkgs_sa-0.1.0.dist-info/RECORD
